[
  {
    "id": 1,
    "title": "🏛️ Stockholms Stadshus – nationalromantik vid vattnet",
    "description": "När Ragnar Östberg ritade Stockholms stadshus (invigt 1923) skapade han ett verk som är lika mycket ett monument över Sverige som en funktionell byggnad. Med sin 106 meter höga tornspira, krönt av de tre gyllene kronorna, är huset ett av landets mest kända landmärken.",
    "image": "https://images.unsplash.com/photo-1509356843151-3e7d96241e11?ixlib=rb-1.2.1&auto=format&fit=crop&w=800&q=80",
    "link": "stockholms-stadshus.html",
    "content": "",
    "date": "2024-01-15"
  },
  {
    "id": 2,
    "title": "Eiffeltornet - Från kontrovers till ikon",
    "description": "Upptäck hur Paris mest kända landmärke gick från att vara kontroversiellt till att bli en av världens mest älskade byggnader.",
    "image": "https://images.unsplash.com/photo-1541336032412-2048a678540d?ixlib=rb-1.2.1&auto=format&fit=crop&w=800&q=80",
    "link": "#",
    "content": "",
    "date": "2024-01-10"
  },
  {
    "id": 3,
    "title": "Turning Torso – skyskrapan som vrider sig mot framtiden",
    "description": "När Santiago Calatrava ritade Turning Torso (färdig 2005) satte Malmö Sverige på världskartan för modern arkitektur. Med sina 190 meter är byggnaden Nordens högsta skyskrapa och ett exempel på innovativ ingenjörskonst.",
    "image": "https://images.unsplash.com/photo-1513581166391-887a96ddeafd?ixlib=rb-1.2.1&auto=format&fit=crop&w=800&q=80",
    "link": "turning-torso.html",
    "content": "",
    "date": "2024-01-05"
  },
  {
    "id": 4,
    "title": "Gamla Stan - Stockholms historiska hjärta",
    "description": "En guide till de bästa tipspromenaderna i Stockholms medeltida stadskärna och dess fascinerande arkitekturhistoria.",
    "image": "https://images.unsplash.com/photo-1503386435952-d7918b99d4c5?ixlib=rb-1.2.1&auto=format&fit=crop&w=800&q=80",
    "link": "#",
    "content": "",
    "date": "2023-12-28"
  },
  {
    "id": 5,
    "title": "Drottningholms Slott – svensk barock i världsklass",
    "description": "Vid Mälarens strand utanför Stockholm ligger Drottningholms slott, uppfört på 1600-talet av arkitekten Nicodemus Tessin d.ä. för drottning Hedvig Eleonora. Idag både kungafamiljens bostad och ett världsarv på UNESCO:s lista.",
    "image": "https://images.unsplash.com/photo-1583037189850-1921ae7c6c22?ixlib=rb-1.2.1&auto=format&fit=crop&w=800&q=80",
    "link": "drottningholms-slott.html",
    "content": "",
    "date": "2023-12-20"
  },
  {
    "id": 6,
    "title": "Burj Khalifa - Teknikens under",
    "description": "Hur byggde man världens högsta byggnad? Utforska den banbrytande tekniken bakom Dubais ikoniska skyskrapa.",
    "image": "https://images.unsplash.com/photo-1505902987837-7b8f4ff9c1e2?ixlib=rb-1.2.1&auto=format&fit=crop&w=800&q=80",
    "link": "#",
    "content": "",
    "date": "2023-12-15"
  }
]
